Workbook

Sheet 📊 Dashboard
A1: ✨ SMART EVENT PLANNER PRO — Primavera Events Group
A2: Tu herramienta profesional de planeación de eventos
A4: ⚙️ CONFIGURACIÓN DEL EVENTO
A5: Nombre del evento | B5: Boda Sofía & Rodrigo | C5: ⏳ Días para el evento:
A6: Tipo de evento | B6: Boda | C6: =IF(B7="","—",MAX(0,B7-TODAY()))
A7: Fecha del evento | B7: 45976 | C7: días restantes
A8: Lugar | B8: Hacienda La Primavera, Morelos
A9: Número de invitados | B9: 150
A10: Presupuesto total ($MXN) | B10: 180000
A12: 💰 PRESUPUESTO GASTADO | D12: ✅ TAREAS COMPLETADAS | G12: 👥 INVITADOS CONFIRMADOS | J12: 📦 SERVICIOS SELEC.
A13: =IFERROR('💰 Presupuesto'!H52,0) | D13: =COUNTIF('✅ Checklist'!E5:E60,"✓") | G13: =COUNTIF('👥 Invitados'!D5:D204,"Sí") | J13: =COUNTIF('📦 Catálogo'!G5:G116,"✓")
A15: 💰 RESUMEN DE PRESUPUESTO | G15: ⚠️ ALERTAS INTELIGENTES
A16: Presupuesto Total | B16: =B10 | G16: =IF(AND(B7-TODAY()<90,COUNTIF('📦 Catálogo'!B5:B120,"*fotógrafo*")+COUNTIF('📦 Catálogo'!G5:G120,"✓")=0),"🔴 Faltan menos de 90 días y no tienes fotógrafo","🟢 Fotografía en orden")
A17: Total Estimado (Catálogo) | B17: =IFERROR('💰 Presupuesto'!E58,0) | G17: =IF(B7-TODAY()<60,"🟠 Faltan menos de 60 días — confirma DJ y música","🟢 Música en orden")
A18: Total Real (Gastado) | B18: =IFERROR('💰 Presupuesto'!G58,0) | G18: =IF(IFERROR(B18/B16,0)>0.8,"🔴 Superaste el 80% del presupuesto","🟢 Presupuesto bajo control")
A19: Total Anticipos Pagados | B19: =IFERROR('💰 Presupuesto'!H58,0) | G19: =IF(AND(B7-TODAY()<30,IFERROR(COUNTIF('👥 Invitados'!D5:D204,"Sí")/B9,0)<0.5),"🟡 Menos del 50% de confirmaciones a 30 días","🟢 Confirmaciones en orden")
A20: Saldo Pendiente | B20: =IFERROR('💰 Presupuesto'!I58,0) | G20: =IF(B7-TODAY()<7,"🔴 ¡SEMANA DEL EVENTO! Verifica últimos pagos y logística","🟢 Aún hay tiempo")
A21: Disponible (Presupuesto-Estimado) | B21: =B16-B17
A22: % Presupuesto Utilizado | B22: =IFERROR(B18/B16,0)

Sheet 💰 Presupuesto
A1: 💰 PRESUPUESTO DEL EVENTO
A2: Gestiona costos estimados, reales y saldos pendientes
A3: N° | B3: Categoría | C3: Servicio / Proveedor | D3: Descripción | E3: Costo Estimado | F3: % del Total | G3: Costo Real | H3: Anticipo Pagado | I3: Saldo Pendiente | J3: Estado | K3: Notas
A4: 🏛️ Locación & Logística
A5: 1 | B5: 🏛️ Locación & Logística | C5: Salón de eventos — Hacienda La Primavera | E5: 45000 | F5: =IFERROR(E5/E$58,0) | G5: 45000 | H5: 20000 | I5: =IFERROR(G5-H5,0) | J5: Anticipo pagado
A6: 2 | B6: 🏛️ Locación & Logística | C6: Valet Parking — Staff Externo | E6: 5000 | F6: =IFERROR(E6/E$58,0) | G6: 5000 | H6: 2000 | I6: =IFERROR(G6-H6,0) | J6: Anticipo pagado
A7: 3 | B7: 🏛️ Locación & Logística | C7: Generador eléctrico — Rentas López | E7: 3500 | F7: =IFERROR(E7/E$58,0) | G7: 3500 | H7: 0 | I7: =IFERROR(G7-H7,0) | J7: Pendiente
A8: 4 | B8: 🏛️ Locación & Logística | C8: Seguridad privada — SecureEvents | E8: 4000 | F8: =IFERROR(E8/E$58,0) | G8: 4000 | H8: 4000 | I8: =IFERROR(G8-H8,0) | J8: Pagado
A9: 🍽️ Banquete & Bebidas
A10: 5 | B10: 🍽️ Banquete & Bebidas | C10: Banquete 3 tiempos — Catering Gourmet MX | E10: 35000 | F10: =IFERROR(E10/E$58,0) | G10: 35000 | H10: 15000 | I10: =IFERROR(G10-H10,0) | J10: Anticipo pagado
A11: 6 | B11: 🍽️ Banquete & Bebidas | C11: Pastel de bodas — Dulcería Arte | E11: 8000 | F11: =IFERROR(E11/E$58,0) | G11: 8500 | H11: 4000 | I11: =IFERROR(G11-H11,0) | J11: Anticipo pagado
A12: 7 | B12: 🍽️ Banquete & Bebidas | C12: Barra libre — Bar Móvil Premium | E12: 12000 | F12: =IFERROR(E12/E$58,0) | G12: 12000 | H12: 6000 | I12: =IFERROR(G12-H12,0) | J12: Anticipo pagado
A13: 8 | B13: 🍽️ Banquete & Bebidas | C13: Taquiza madrugada — Tacos El Compadre | E13: 6000 | F13: =IFERROR(E13/E$58,0) | G13: 6000 | H13: 0 | I13: =IFERROR(G13-H13,0) | J13: Pendiente
A14: 🎧 Entretenimiento
A15: 9 | B15: 🎧 Entretenimiento | C15: DJ profesional — DJ Alex Beats | E15: 8000 | F15: =IFERROR(E15/E$58,0) | G15: 8000 | H15: 4000 | I15: =IFERROR(G15-H15,0) | J15: Anticipo pagado
A16: 10 | B16: 🎧 Entretenimiento | C16: Mariachi — Mariachi Sol de México | E16: 6000 | F16: =IFERROR(E16/E$58,0) | G16: 6000 | H16: 6000 | I16: =IFERROR(G16-H16,0) | J16: Pagado
A17: 11 | B17: 🎧 Entretenimiento | C17: Show sorpresa — Batucada Ritmo Vivo | E17: 5000 | F17: =IFERROR(E17/E$58,0) | G17: 5000 | H17: 0 | I17: =IFERROR(G17-H17,0) | J17: Pendiente
A18: 12 | B18: 🎧 Entretenimiento | C18: Maestro de ceremonias — MC Eventos Pro | E18: 3500 | F18: =IFERROR(E18/E$58,0) | G18: 3500 | H18: 3500 | I18: =IFERROR(G18-H18,0) | J18: Pagado
A19: 📸 Foto & Video
A20: 13 | B20: 📸 Foto & Video | C20: Fotógrafo — Luis Mendoza Photography | E20: 15000 | F20: =IFERROR(E20/E$58,0) | G20: 15000 | H20: 7500 | I20: =IFERROR(G20-H20,0) | J20: Anticipo pagado
A21: 14 | B21: 📸 Foto & Video | C21: Videógrafo + Drone — Pixel Films | E21: 12000 | F21: =IFERROR(E21/E$58,0) | G21: 12000 | H21: 6000 | I21: =IFERROR(G21-H21,0) | J21: Anticipo pagado
A22: 15 | B22: 📸 Foto & Video | C22: Same Day Edit — Pixel Films | E22: 3000 | F22: =IFERROR(E22/E$58,0) | G22: 3000 | H22: 0 | I22: =IFERROR(G22-H22,0) | J22: Pendiente
A23: 💄 Belleza & Imagen
A24: 16 | B24: 💄 Belleza & Imagen | C24: Maquillista — Glam Studio | E24: 4500 | F24: =IFERROR(E24/E$58,0) | G24: 4500 | H24: 2000 | I24: =IFERROR(G24-H24,0) | J24: Anticipo pagado
A25: 17 | B25: 💄 Belleza & Imagen | C25: Peinadora / Estilista — Glam Studio | E25: 3500 | F25: =IFERROR(E25/E$58,0) | G25: 3500 | H25: 1500 | I25: =IFERROR(G25-H25,0) | J25: Anticipo pagado
A26: 18 | B26: 💄 Belleza & Imagen | C26: Barbero (novio) — Barber Kings | E26: 800 | F26: =IFERROR(E26/E$58,0) | G26: 800 | H26: 800 | I26: =IFERROR(G26-H26,0) | J26: Pagado
A27: 👗 Vestuario
A28: 19 | B28: 👗 Vestuario | C28: Vestido de novia — Bridal House Cuernavaca | E28: 18000 | F28: =IFERROR(E28/E$58,0) | G28: 18000 | H28: 9000 | I28: =IFERROR(G28-H28,0) | J28: Anticipo pagado
A29: 20 | B29: 👗 Vestuario | C29: Traje del novio — Fashion Men | E29: 6000 | F29: =IFERROR(E29/E$58,0) | G29: 6000 | H29: 3000 | I29: =IFERROR(G29-H29,0) | J29: Anticipo pagado
A30: 21 | B30: 👗 Vestuario | C30: Vestidos de damas (5) — Boutique Elegance | E30: 7500 | F30: =IFERROR(E30/E$58,0) | G30: 7500 | H30: 3500 | I30: =IFERROR(G30-H30,0) | J30: Anticipo pagado
A31: 💃 Coreografía & Show
A32: 22 | B32: 💃 Coreografía & Show | C32: Coreógrafo — Dance Academy Pro | E32: 4000 | F32: =IFERROR(E32/E$58,0) | G32: 4000 | H32: 2000 | I32: =IFERROR(G32-H32,0) | J32: Anticipo pagado
A33: 23 | B33: 💃 Coreografía & Show | C33: Clases de baile (10 sesiones) — Dance Academy Pro | E33: 3000 | F33: =IFERROR(E33/E$58,0) | G33: 3000 | H33: 3000 | I33: =IFERROR(G33-H33,0) | J33: Pagado
A34: 🌸 Decoración & Diseño
A35: 24 | B35: 🌸 Decoración & Diseño | C35: Decorador principal — Deco Dreams | E35: 15000 | F35: =IFERROR(E35/E$58,0) | G35: 15000 | H35: 7000 | I35: =IFERROR(G35-H35,0) | J35: Anticipo pagado
A36: 25 | B36: 🌸 Decoración & Diseño | C36: Arreglos florales — Floral Art Studio | E36: 8000 | F36: =IFERROR(E36/E$58,0) | G36: 8000 | H36: 4000 | I36: =IFERROR(G36-H36,0) | J36: Anticipo pagado
A37: 26 | B37: 🌸 Decoración & Diseño | C37: Iluminación ambiental — Luz & Ambiente | E37: 5000 | F37: =IFERROR(E37/E$58,0) | G37: 5000 | H37: 2500 | I37: =IFERROR(G37-H37,0) | J37: Anticipo pagado
A38: 27 | B38: 🌸 Decoración & Diseño | C38: Mantelería y vajilla — Rentas Elegance | E38: 4000 | F38: =IFERROR(E38/E$58,0) | G38: 4000 | H38: 0 | I38: =IFERROR(G38-H38,0) | J38: Pendiente
A39: 💌 Papelería & Diseño
A40: 28 | B40: 💌 Papelería & Diseño | C40: Invitaciones físicas (200) — Imprenta Creativa | E40: 3500 | F40: =IFERROR(E40/E$58,0) | G40: 3500 | H40: 3500 | I40: =IFERROR(G40-H40,0) | J40: Pagado
A41: 29 | B41: 💌 Papelería & Diseño | C41: Invitaciones digitales — Design Studio | E41: 1500 | F41: =IFERROR(E41/E$58,0) | G41: 1500 | H41: 1500 | I41: =IFERROR(G41-H41,0) | J41: Pagado
A42: 30 | B42: 💌 Papelería & Diseño | C42: Señalética del evento — Design Studio | E42: 1200 | F42: =IFERROR(E42/E$58,0) | G42: 1200 | H42: 0 | I42: =IFERROR(G42-H42,0) | J42: Pendiente
A43: 🚗 Transporte
A44: 31 | B44: 🚗 Transporte | C44: Transporte invitados (2 vans) — Trans VIP | E44: 5000 | F44: =IFERROR(E44/E$58,0) | G44: 5000 | H44: 2500 | I44: =IFERROR(G44-H44,0) | J44: Anticipo pagado
A45: 32 | B45: 🚗 Transporte | C45: Limusina novios — Limo Service MX | E45: 4500 | F45: =IFERROR(E45/E$58,0) | G45: 4500 | H45: 4500 | I45: =IFERROR(G45-H45,0) | J45: Pagado
A46: 🧑 Staff Operativo
A47: 33 | B47: 🧑 Staff Operativo | C47: Meseros (10) — Staff Events | E47: 8000 | F47: =IFERROR(E47/E$58,0) | G47: 8000 | H47: 0 | I47: =IFERROR(G47-H47,0) | J47: Pendiente
A48: 34 | B48: 🧑 Staff Operativo | C48: Hostess (4) — Staff Events | E48: 3200 | F48: =IFERROR(E48/E$58,0) | G48: 3200 | H48: 0 | I48: =IFERROR(G48-H48,0) | J48: Pendiente
A49: 35 | B49: 🧑 Staff Operativo | C49: Coordinador día del evento — Primavera Events Group | E49: 5000 | F49: =IFERROR(E49/E$58,0) | G49: 5000 | H49: 5000 | I49: =IFERROR(G49-H49,0) | J49: Pagado
A50: 🎁 Experiencia & Extras
A51: 36 | B51: 🎁 Experiencia & Extras | C51: Souvenirs (150) — Recuerdos MX | E51: 4500 | F51: =IFERROR(E51/E$58,0) | G51: 4500 | H51: 0 | I51: =IFERROR(G51-H51,0) | J51: Pendiente
A52: 37 | B52: 🎁 Experiencia & Extras | C52: Letras gigantes LED — Deco Dreams | E52: 2500 | F52: =IFERROR(E52/E$58,0) | G52: 2500 | H52: 2500 | I52: =IFERROR(G52-H52,0) | J52: Pagado
A53: 38 | B53: 🎁 Experiencia & Extras | C53: Fuegos artificiales fríos — Pirotecnia Arte | E53: 3000 | F53: =IFERROR(E53/E$58,0) | G53: 3000 | H53: 0 | I53: =IFERROR(G53-H53,0) | J53: Pendiente
A54: 🧾 Administrativo
A55: 39 | B55: 🧾 Administrativo | C55: Seguro del evento — Seguros Eventos | E55: 2000 | F55: =IFERROR(E55/E$58,0) | G55: 2000 | H55: 2000 | I55: =IFERROR(G55-H55,0) | J55: Pagado
A56: 40 | B56: 🧾 Administrativo | C56: Gastos imprevistos — — | E56: 5000 | F56: =IFERROR(E56/E$58,0) | G56: 0 | H56: 0 | I56: =IFERROR(G56-H56,0) | J56: Pendiente
A58: TOTALES GENERALES | E58: =SUM(E4:E57) | F58: ="100%" | G58: =SUM(G4:G57) | H58: =SUM(H4:H57) | I58: =SUM(I4:I57)

Sheet 📦 Catálogo
A1: 📦 CATÁLOGO COMPLETO DE SERVICIOS
A2: Selecciona los servicios — se reflejarán en el presupuesto automáticamente
A3: N° | B3: Categoría | C3: Servicio | D3: Descripción | E3: Costo Est. ($) | F3: Prioridad | G3: Seleccionado | H3: Notas
A4: Locacion & Logistica
A5: 1 | B5: Locacion & Logistica | C5: Centro de Convenciones Presidente (Salón de Gala) | D5: Espacio premium de gran capacidad para bodas y XV años de gala. | E5: 111150 | F5: Alta | G5: — | H5: =HYPERLINK("https://primaveraeventsgroup.com/venues/","Ver Centro Presidente")
A6: 2 | B6: Locacion & Logistica | C6: Salón Primavera Events - Paquete Básico | D6: Salón cerrado oficial con equipamiento, mantelería de lujo y banquete básico. | E6: 52650 | F6: Alta | G6: — | H6: =HYPERLINK("https://primaveraeventsgroup.com/venues/","Ver Salón Primavera")
A7: 3 | B7: Locacion & Logistica | C7: Salón Primavera Events - Paquete Premium | D7: Salón oficial con banquete 3 tiempos, decoración floral y coordinación. | E7: 76050 | F7: Alta | G7: — | H7: =HYPERLINK("https://primaveraeventsgroup.com/venues/","Ver Salón Primavera")
A8: 4 | B8: Locacion & Logistica | C8: Salón Primavera Events - Paquete VIP | D8: Salón oficial todo incluido: banquete gala, dj, iluminación y coordinación total. | E8: 99450 | F8: Alta | G8: — | H8: =HYPERLINK("https://primaveraeventsgroup.com/venues/","Ver Salón Primavera")
A9: 5 | B9: Locacion & Logistica | C9: Salón Calesa Eventos - Paquete Básico | D9: Salón cerrado tradicional para banquetes y recepciones de gran prestigio. | E9: 46800 | F9: Alta | G9: — | H9: =HYPERLINK("https://primaveraeventsgroup.com/venues/","Ver Salón Calesa")
A10: 6 | B10: Locacion & Logistica | C10: Salón Calesa Eventos - Paquete Premium | D10: Salón cerrado tradicional con banquete de 3 tiempos y ambientación de gala. | E10: 70200 | F10: Alta | G10: — | H10: =HYPERLINK("https://primaveraeventsgroup.com/venues/","Ver Salón Calesa")
A11: 7 | B11: Locacion & Logistica | C11: Permisos municipales | D11: Trámites legales para el evento. | E11: 2000 | F11: Alta | G11: —
A12: 8 | B12: Locacion & Logistica | C12: Planta de luz / Generador | D12: Respaldo eléctrico garantizado. | E12: 3500 | F12: Alta | G12: —
A13: 9 | B13: Locacion & Logistica | C13: Sanitarios móviles | D13: Servicio de sanitarios portátiles de lujo. | E13: 2500 | F13: Media | G13: —
A14: 10 | B14: Locacion & Logistica | C14: Estacionamiento / Valet parking | D14: Servicio de estacionamiento para invitados. | E14: 5000 | F14: Media | G14: —
A15: 11 | B15: Logistica | C15: Seguridad privada | D15: Personal de seguridad certificado para el evento. | E15: 4000 | F15: Alta | G15: —
A16: 12 | B16: Logistica | C16: Protección civil | D16: Dictamen y requerimientos para eventos masivos. | E16: 1500 | F16: Alta | G16: —
A17: Banquete & Bebidas
A18: 13 | B18: Banquete & Bebidas | C18: Banquetes Primavera - Gala 3 Tiempos | D18: Entrada, plato fuerte y postre. Vajilla, cristalería y servicio de gala. | E18: 40950 | F18: Alta | G18: — | H18: =HYPERLINK("https://primaveraeventsgroup.com/987509796-2/banquetes-primavera/","Ver Banquetes Primavera")
A19: 14 | B19: Banquete & Bebidas | C19: Banquetes Primavera - Buffet Especial | D19: Variedad de guisados de gala a libre servicio para tus invitados. | E19: 32760 | F19: Alta | G19: — | H19: =HYPERLINK("https://primaveraeventsgroup.com/987509796-2/banquetes-primavera/","Ver Banquetes Primavera")
A20: 15 | B20: Banquete & Bebidas | C20: Banquetes Primavera - Tornaboda Chilaquiles | D20: Chilaquiles rojos/verdes al cierre del evento (100 personas). | E20: 7020 | F20: Media | G20: — | H20: =HYPERLINK("https://primaveraeventsgroup.com/987509796-2/banquetes-primavera/","Ver Banquetes Primavera")
A21: 16 | B21: Banquete & Bebidas | C21: Mesa de postres | D21: Variedad de dulces y postres artesanales montados sobre mesa temática. | E21: 4500 | F21: Media | G21: —
A22: 17 | B22: Banquete & Bebidas | C22: Pastel de bodas/XV | D22: Pastel artístico o tradicional diseñado a medida. | E22: 8000 | F22: Alta | G22: —
A23: 18 | B23: Banquete & Bebidas | C23: Candy bar | D23: Barra de golosinas y dulces decorativa. | E23: 3500 | F23: Media | G23: —
A24: 19 | B24: Banquete & Bebidas | C24: Barra libre | D24: Bebidas nacionales ilimitadas durante 5 horas. | E24: 12000 | F24: Alta | G24: —
A25: 20 | B25: Banquete & Bebidas | C25: Mixología Primavera | D25: Cócteles artesanales y presentaciones con alcohol y sin alcohol. | E25: 5000 | F25: Media | G25: —
A26: 21 | B26: Banquete & Bebidas | C26: Paleteria La Princesa - Paquete 1 | D26: Carrito personalizado con 150 mini paletas tradicionales de fruta natural. | E26: 1989 | F26: Media | G26: — | H26: =HYPERLINK("https://wa.me/527772141981","Pedir La Princesa")
A27: 22 | B27: Banquete & Bebidas | C27: Paleteria La Princesa - Paquete 2 | D27: Servicio de Nieve y Helado artesanal de Michoacán para 100 personas. | E27: 4212 | F27: Media | G27: — | H27: =HYPERLINK("https://wa.me/527772141981","Pedir La Princesa")
A28: 23 | B28: Banquete & Bebidas | C28: Paleteria La Princesa - Paquete 3 | D28: Servicio Mixto: 75 mini paletas + Helado/Nieve para 50 personas. | E28: 3042 | F28: Media | G28: — | H28: =HYPERLINK("https://wa.me/527772141981","Pedir La Princesa")
A29: 24 | B29: Banquete & Bebidas | C29: Tequila Don Ramón - Luis Miguel Plata | D29: Botella Cerámica Personalizada con grabado punta diamante (Plata). | E29: 6435 | F29: Alta | G29: — | H29: =HYPERLINK("https://wa.me/527771204557","Pedir Don Ramon")
A30: 25 | B30: Banquete & Bebidas | C30: Tequila Don Ramón - Luis Miguel Reposado | D30: Botella Cerámica Personalizada con grabado punta diamante (Reposado). | E30: 7465 | F30: Alta | G30: — | H30: =HYPERLINK("https://wa.me/527771204557","Pedir Don Ramon")
A31: 26 | B31: Banquete & Bebidas | C31: Tequila Don Ramón - Luis Miguel Añejo | D31: Botella Cerámica Personalizada con grabado punta diamante (Añejo). | E31: 8752 | F31: Alta | G31: — | H31: =HYPERLINK("https://wa.me/527771204557","Pedir Don Ramon")
A32: 27 | B32: Banquete & Bebidas | C32: Tequila Don Ramón - Swarovski Plata | D32: Edición Coleccionista con cristales incrustados (Plata). | E32: 9565 | F32: Alta | G32: — | H32: =HYPERLINK("https://wa.me/527771204557","Pedir Don Ramon")
A33: 28 | B33: Banquete & Bebidas | C33: Tequila Don Ramón - Swarovski Añejo | D33: Edición Coleccionista con cristales incrustados (Añejo). | E33: 10723 | F33: Alta | G33: — | H33: =HYPERLINK("https://wa.me/527771204557","Pedir Don Ramon")
A34: 29 | B34: Banquete & Bebidas | C34: Tequila Don Ramón - Swarovski Extra Añejo | D34: Edición Coleccionista con cristales incrustados (Extra Añejo). | E34: 12525 | F34: Alta | G34: — | H34: =HYPERLINK("https://wa.me/527771204557","Pedir Don Ramon")
A35: Entretenimiento
A36: 30 | B36: Entretenimiento | C36: Scanner DJ - Paquete Básico | D36: DJ profesional, audio estándar e iluminación LED. | E36: 11700 | F36: Alta | G36: — | H36: =HYPERLINK("https://wa.me/527771992434","Pedir Scanner DJ")
A37: 31 | B37: Entretenimiento | C37: Scanner DJ - Paquete Intermedio | D37: Audio premium, cabina de DJ iluminada y luces robóticas. | E37: 17550 | F37: Alta | G37: — | H37: =HYPERLINK("https://wa.me/527771992434","Pedir Scanner DJ")
A38: 32 | B38: Entretenimiento | C38: Scanner DJ - Paquete Completo | D38: Mega producción de audio, pantallas y show de luces robotizadas. | E38: 23400 | F38: Alta | G38: — | H38: =HYPERLINK("https://wa.me/527771992434","Pedir Scanner DJ")
A39: 33 | B39: Entretenimiento | C39: Corona Music - Paquete Mediano | D39: DJ, Iluminación profesional y audio de alta fidelidad. | E39: 10530 | F39: Alta | G39: — | H39: =HYPERLINK("https://wa.me/527774458481","Pedir Corona Music")
A40: 34 | B40: Entretenimiento | C40: Corona Music - Paquete VIP | D40: Producción de audio premium, pantallas LED, cabina y pista iluminada. | E40: 18720 | F40: Alta | G40: — | H40: =HYPERLINK("https://wa.me/527774458481","Pedir Corona Music")
A41: 35 | B41: Entretenimiento | C41: Mariachi Xiuhtepetl - Dos Horas | D41: Show de Mariachi tradicional completo con arpa en vivo (2 horas). | E41: 11115 | F41: Media | G41: — | H41: =HYPERLINK("https://wa.me/527771204557","Pedir Mariachi")
A42: 36 | B42: Entretenimiento | C42: Mariachi Xiuhtepetl - Una Hora | D42: Show de Mariachi tradicional completo con arpa en vivo (1 hora). | E42: 5850 | F42: Media | G42: — | H42: =HYPERLINK("https://wa.me/527771204557","Pedir Mariachi")
A43: 37 | B43: Entretenimiento | C43: Mariachi Xiuhtepetl - Set 45 Min | D43: Set rápido de 45 minutos ideal para cenas o recepciones. | E43: 5265 | F43: Media | G43: — | H43: =HYPERLINK("https://wa.me/527771204557","Pedir Mariachi")
A44: 38 | B44: Entretenimiento | C44: Mariachi Xiuhtepetl - Serenata | D44: Serenata tradicional completa de 10 canciones. | E44: 4680 | F44: Media | G44: — | H44: =HYPERLINK("https://wa.me/527771204557","Pedir Mariachi")
A45: 39 | B45: Entretenimiento | C45: Mariachi Xiuhtepetl - Serenata Corta | D45: Serenata corta de 5 canciones. | E45: 4095 | F45: Media | G45: — | H45: =HYPERLINK("https://wa.me/527771204557","Pedir Mariachi")
A46: 40 | B46: Entretenimiento | C46: Saxofonista | D46: Música de saxofón en vivo para el banquete o cocktail. | E46: 3500 | F46: Media | G46: —
A47: 41 | B47: Entretenimiento | C47: Violinista | D47: Música instrumental de violín para ceremonia o cena. | E47: 3000 | F47: Media | G47: —
A48: 42 | B48: Entretenimiento | C48: Batucada | D48: Show interactivo de percusión con globos y antifaces. | E48: 5000 | F48: Media | G48: —
A49: 43 | B49: Entretenimiento | C49: Cabina de fotos / Photo booth | D49: Fotos instantáneas con accesorios de diversión. | E49: 4500 | F49: Media | G49: —
A50: Foto & Video
A51: 44 | B51: Foto & Video | C51: Licky Baut Photo - Cobertura Básica | D51: Cobertura de fotografía digital para ceremonia y banquete (5 horas). | E51: 9360 | F51: Alta | G51: — | H51: =HYPERLINK("https://wa.me/527772967139","Pedir Licky Baut")
A52: 45 | B52: Foto & Video | C52: Licky Baut Photo - Cinema VIP | D52: Fotografía profesional + video cinematográfico editado + drone (toda la gala). | E52: 21060 | F52: Alta | G52: — | H52: =HYPERLINK("https://wa.me/527772967139","Pedir Licky Baut")
A53: 46 | B53: Foto & Video | C53: Drone | D53: Tomas aéreas de video en alta definición de la locación y el evento. | E53: 4000 | F53: Media | G53: —
A54: 47 | B54: Foto & Video | C54: Same Day Edit | D54: Video resumen proyectado antes de finalizar el evento. | E54: 3000 | F54: Media | G54: —
A55: 48 | B55: Foto & Video | C55: Sesión pre-evento | D55: Sesión fotográfica artística previa para novios o quinceañera. | E55: 3500 | F55: Media | G55: —
A56: 49 | B56: Foto & Video | C56: Álbum impreso | D56: Álbum fotográfico profesional de pasta dura personalizado. | E56: 4500 | F56: Media | G56: —
A57: Belleza & Imagen
A58: 50 | B58: Belleza & Imagen | C58: Andrea Lozano - Paquete Plus Novia | D58: Maquillaje aerógrafo en rostro, peinado, ampolleta de lifting e hidratación. | E58: 10413 | F58: Alta | G58: — | H58: =HYPERLINK("https://wa.me/527774587923","Pedir Andrea Lozano")
A59: 51 | B59: Belleza & Imagen | C59: Andrea Lozano - Paquete Power Novia | D59: Maquillaje aerógrafo profesional y peinado de gala con tocado. | E59: 9009 | F59: Alta | G59: — | H59: =HYPERLINK("https://wa.me/527774587923","Pedir Andrea Lozano")
A60: 52 | B60: Belleza & Imagen | C60: Andrea Lozano - Paquete Básico Novia | D60: Maquillaje tradicional con pestañas y peinado profesional. | E60: 8424 | F60: Alta | G60: — | H60: =HYPERLINK("https://wa.me/527774587923","Pedir Andrea Lozano")
A61: 53 | B61: Belleza & Imagen | C61: Andrea Lozano - Maquillaje Aerógrafo Novia Ind | D61: Maquillaje aerógrafo individual para novia/quinceañera. | E61: 2960 | F61: Media | G61: — | H61: =HYPERLINK("https://wa.me/527774587923","Pedir Andrea Lozano")
A62: 54 | B62: Belleza & Imagen | C62: Andrea Lozano - Maquillaje Tradicional Novia Ind | D62: Maquillaje tradicional individual para novia/quinceañera. | E62: 2831 | F62: Media | G62: — | H62: =HYPERLINK("https://wa.me/527774587923","Pedir Andrea Lozano")
A63: 55 | B63: Belleza & Imagen | C63: Andrea Lozano - Peinado Novia Individual | D63: Peinado de novia individual con colocación de tocado y velo. | E63: 2457 | F63: Media | G63: — | H63: =HYPERLINK("https://wa.me/527774587923","Pedir Andrea Lozano")
A64: 56 | B64: Belleza & Imagen | C64: Andrea Lozano - Peinado + Aero Invitadas | D64: Servicio a domicilio de peinado y maquillaje aerógrafo para acompañantes. | E64: 2867 | F64: Media | G64: — | H64: =HYPERLINK("https://wa.me/527774587923","Pedir Andrea Lozano")
A65: 57 | B65: Belleza & Imagen | C65: Andrea Lozano - Peinado + Tradicional Invitadas | D65: Servicio a domicilio de peinado y maquillaje tradicional para acompañantes. | E65: 2574 | F65: Media | G65: — | H65: =HYPERLINK("https://wa.me/527774587923","Pedir Andrea Lozano")
A66: 58 | B66: Belleza & Imagen | C66: Barbero (novio) | D66: Corte y arreglo de barba profesional para el novio el gran día. | E66: 800 | F66: Media | G66: —
A67: 59 | B67: Belleza & Imagen | C67: Spa / Tratamientos previos | D67: Sesiones faciales y de relajación pre-boda. | E67: 2500 | F67: Media | G67: —
A68: Vestuario
A69: 60 | B69: Vestuario | C69: Vestido de novia / XV | D69: Vestido de gala principal seleccionado. | E69: 18000 | F69: Alta | G69: —
A70: 61 | B70: Vestuario | C70: Traje del novio | D70: Traje sastre o smoking premium. | E70: 6000 | F70: Alta | G70: —
A71: 62 | B71: Vestuario | C71: Vestidos de damas | D71: Lote de vestidos para las damas de honor. | E71: 7500 | F71: Media | G71: —
A72: 63 | B72: Vestuario | C72: Renta de smoking | D72: Smoking para los chambelanes o familiares. | E72: 3000 | F72: Media | G72: —
A73: 64 | B73: Vestuario | C73: Accesorios (velo, tiara, etc.) | D73: Accesorios de novia/quinceañera. | E73: 2500 | F73: Media | G73: —
A74: 65 | B74: Vestuario | C74: Zapatos | D74: Calzado especial cómodo y de gala. | E74: 2000 | F74: Media | G74: —
A75: Coreografia & Show
A76: 66 | B76: Coreografia & Show | C76: Dance Queens - Paquete Vals Básico | D76: Coreografía oficial del vals, 6 clases de ensayo y copas decoradas de regalo. | E76: 7605 | F76: Alta | G76: — | H76: =HYPERLINK("https://wa.me/527772994425","Pedir Dance Queens")
A77: 67 | B77: Coreografia & Show | C77: Dance Queens - Paquete Vals VIP | D77: Coreografía Vals, moderna y show con pirotecnia fría e hidrogel led (10 clases). | E77: 11115 | F77: Alta | G77: — | H77: =HYPERLINK("https://wa.me/527772994425","Pedir Dance Queens")
A78: 68 | B78: Coreografia & Show | C78: Ensayos grupales extras | D78: Clases adicionales para repasar pasos y sincronización. | E78: 1500 | F78: Alta | G78: —
A79: Decoracion & Diseno
A80: 69 | B80: Decoracion & Diseno | C80: Jessy & Richard - Coordinación Básica | D80: Planificación inicial de presupuesto, proveedores y timing de la boda. | E80: 17550 | F80: Alta | G80: — | H80: =HYPERLINK("https://primaveraeventsgroup.com/987509796-2/wedding-event-planning/","Ver Jessy & Richard")
A81: 70 | B81: Decoracion & Diseno | C81: Jessy & Richard - Coordinación Full VIP | D81: Coordinación y producción total de inicio a fin del evento en la locación. | E81: 35100 | F81: Alta | G81: — | H81: =HYPERLINK("https://primaveraeventsgroup.com/987509796-2/wedding-event-planning/","Ver Jessy & Richard")
A82: 71 | B82: Decoracion & Diseno | C82: Kataleya Florist - Ramo de Novia Premium | D82: Arreglo floral exclusivo con flores de gala importadas y orquídeas. | E82: 32760 | F82: Alta | G82: — | H82: =HYPERLINK("https://wa.me/527775114425","Pedir Kataleya")
A83: 72 | B83: Decoracion & Diseno | C83: Kataleya Florist - Centros de Mesa Gala | D83: Arreglos florales frescos de altura para mesas de comensales. | E83: 995 | F83: Alta | G83: — | H83: =HYPERLINK("https://wa.me/527775114425","Pedir Kataleya")
A84: 73 | B84: Decoracion & Diseno | C84: Kataleya Florist - Decoración de Altar/Ceremonia | D84: Set de flores de gala y decoración para pasillo y altar. | E84: 8775 | F84: Alta | G84: — | H84: =HYPERLINK("https://wa.me/527775114425","Pedir Kataleya")
A85: 74 | B85: Decoracion & Diseno | C85: Aby Decora - Bouquet 15 Años | D85: Montaje decorativo de globos con número gigante de 15 años. | E85: 2925 | F85: Media | G85: — | H85: =HYPERLINK("https://wa.me/527774587923","Pedir Aby Decora")
A86: 75 | B86: Decoracion & Diseno | C86: Aby Decora - Montaje Arco Globos | D86: Arco orgánico de globos premium para entrada o mesa de honor. | E86: 3510 | F86: Media | G86: — | H86: =HYPERLINK("https://wa.me/527774587923","Pedir Aby Decora")
A87: 76 | B87: Decoracion & Diseno | C87: Aby Decora - Panel Back Globos | D87: Panel circular con set de globos y luces de neón decorativas. | E87: 5265 | F87: Media | G87: — | H87: =HYPERLINK("https://wa.me/527774587923","Pedir Aby Decora")
A88: 77 | B88: Decoracion & Diseno | C88: Aby Decora - Decoración Total Globos | D88: Decoración total: Mesa de honor, mesa de dulces, back y entrada. | E88: 5850 | F88: Media | G88: — | H88: =HYPERLINK("https://wa.me/527774587923","Pedir Aby Decora")
A89: 78 | B89: Decoracion & Diseno | C89: Mobiliario temático | D89: Renta de mesas de madera, sillas crossback o salas lounge. | E89: 4500 | F89: Media | G89: —
A90: 79 | B90: Decoracion & Diseno | C90: Mantelería premium | D90: Manteles de gala, caminos de mesa y servilletas bordadas. | E90: 2500 | F90: Media | G90: —
A91: Produccion & Montaje
A92: 80 | B92: Produccion & Montaje | C92: Proveedor de Pantallas - LED P3 (3x2m) | D92: Pantalla gigante de alta definición con soporte, cableado y operador. | E92: 9945 | F92: Media | G92: — | H92: =HYPERLINK("https://primaveraeventsgroup.com/","Ver Proveedor Pantallas")
A93: 81 | B93: Produccion & Montaje | C93: Proveedor de Pantallas - LED P3 (4x3m) | D93: Pantalla gigante LED P3 premium de gran alcance con operador. | E93: 14040 | F93: Media | G93: — | H93: =HYPERLINK("https://primaveraeventsgroup.com/","Ver Proveedor Pantallas")
A94: 82 | B94: Produccion & Montaje | C94: Iluminación arquitectónica | D94: Montaje de luces ambientales en columnas y áreas clave del salón. | E94: 6000 | F94: Alta | G94: —
A95: 83 | B95: Produccion & Montaje | C95: Audio profesional | D95: Equipamiento de bocinas line array de alta fidelidad para el banquete. | E95: 5000 | F95: Alta | G95: —
A96: 84 | B96: Produccion & Montaje | C96: Estructuras / Tarimas | D96: Montaje de pista y estructuras de aluminio elevadas para luces. | E96: 5000 | F96: Media | G96: —
A97: Papeleria & Diseno Grafico
A98: 85 | B98: Papeleria & Diseno Grafico | C98: INIT Idea - Invitación Digital Premium | D98: Invitación interactiva con música, confirmación, mapa y cronograma. | E98: 1755 | F98: Alta | G98: — | H98: =HYPERLINK("https://5410m0n0c001.github.io/INIT-IDEA/invitaciones.html","Ver INIT Idea")
A99: 86 | B99: Papeleria & Diseno Grafico | C99: INIT Idea - Invitación Digital VIP | D99: Invitación interactiva con pases QR individuales, confirmación y RSVP. | E99: 2925 | F99: Alta | G99: — | H99: =HYPERLINK("https://5410m0n0c001.github.io/INIT-IDEA/invitaciones.html","Ver INIT Idea")
A100: 87 | B100: Papeleria & Diseno Grafico | C100: Invitaciones físicas | D100: Invitaciones impresas en papel fino y sobres personalizados. | E100: 3500 | F100: Alta | G100: —
...

Sheet 👥 Invitados
A1: 👥 LISTA DE INVITADOS
A2: Gestiona confirmaciones, mesas y restricciones alimenticias
A3: Total invitados esperados: | B3: ='📊 Dashboard'!B9 | C3: ✅ Confirmados: | D3: =COUNTIF(D6:D205,"Sí") | E3: ⏳ Pendientes: | F3: =COUNTIF(D6:D205,"Pendiente") | G3: ❌ No asistirán: | H3: =COUNTIF(D6:D205,"No") | I3: 👥 Total personas: | J3: =SUMIF(D6:D205,"Sí",E6:E205)+SUMIF(D6:D205,"Pendiente",E6:E205)
A5: N° | B5: Nombre completo | C5: Familia / Grupo | D5: Confirmación | E5: Acompañantes | F5: Total personas | G5: Mesa asignada | H5: Restricción alimenticia | I5: Teléfono | J5: Notas
A6: 1 | B6: García Martínez | C6: Familia García | D6: Sí | E6: 1 | F6: 2 | G6: Mesa 1 | H6: Ninguna | I6: 55-1234-5678
A7: 2 | B7: López Hernández | C7: Amigos novio | D7: Sí | E7: 0 | F7: 1 | G7: Mesa 2 | H7: Vegetariano | I7: 55-2345-6789
A8: 3 | B8: Rodríguez Pérez | C8: Familia novia | D8: Pendiente | E8: 2 | F8: 3 | H8: Ninguna | I8: 55-3456-7890
A9: 4 | B9: Martínez González | C9: Trabajo | D9: Sí | E9: 1 | F9: 2 | G9: Mesa 3 | H9: Celiaco | I9: 55-4567-8901
A10: 5 | B10: Sánchez Torres | C10: Amigos novia | D10: No | E10: 0 | F10: 1 | H10: Ninguna | I10: 55-5678-9012
A11: 6 | B11: Jiménez Flores | C11: Familia García | D11: Sí | E11: 0 | F11: 1 | G11: Mesa 1 | H11: Alérgico mariscos | I11: 55-6789-0123
A12: 7 | B12: Morales Ruiz | C12: Amigos novio | D12: Pendiente | E12: 1 | F12: 2 | H12: Ninguna | I12: 55-7890-1234
A13: 8 | B13: Hernández Cruz | C13: Trabajo novia | D13: Sí | E13: 1 | F13: 2 | G13: Mesa 4 | H13: Ninguna | I13: 55-8901-2345
A14: 9 | B14: Vázquez Díaz | C14: Familia novia | D14: Sí | E14: 2 | F14: 3 | G14: Mesa 2 | H14: Ninguna | I14: 55-9012-3456
A15: 10 | B15: Reyes Moreno | C15: Amigos | D15: Pendiente | E15: 0 | F15: 1 | H15: Vegetariano | I15: 55-0123-4567
A16: 11 | F16: =IF(D16="","",E16+1)
A17: 12 | F17: =IF(D17="","",E17+1)
A18: 13 | F18: =IF(D18="","",E18+1)
A19: 14 | F19: =IF(D19="","",E19+1)
A20: 15 | F20: =IF(D20="","",E20+1)
A21: 16 | F21: =IF(D21="","",E21+1)
A22: 17 | F22: =IF(D22="","",E22+1)
A23: 18 | F23: =IF(D23="","",E23+1)
A24: 19 | F24: =IF(D24="","",E24+1)
A25: 20 | F25: =IF(D25="","",E25+1)
A26: 21 | F26: =IF(D26="","",E26+1)
A27: 22 | F27: =IF(D27="","",E27+1)
... A205: 200 | F205: =IF(D205="","",E205+1)

Sheet ✅ Checklist
A1: ✅ CHECKLIST POR FASES
A2: Tareas organizadas por etapa — marca ✓ cuando completes cada una
A3: 📊 PROGRESO GENERAL | E3: =COUNTIF(E5:E200,"✓")&" de "&COUNTA(A5:A200)&" tareas completadas" | G3: =IFERROR(COUNTIF(E5:E200,"✓")/COUNTA(A5:A200),0)
A4: N° | B4: Tarea | C4: Responsable | D4: Fecha Límite | E4: Estado | F4: Completado | G4: Notas
A5: 📅 FASE 1: 12-6 MESES ANTES DEL EVENTO
A6: 1 | B6: Definir presupuesto total del evento | C6: Novios/Familia | D6: 12 meses antes | E6: ✓ | F6: =IF(E6="✓","✅ Completado","⏳ Pendiente")
A7: 2 | B7: Elegir y reservar la locación/salón | C7: Novios + Planner | D7: 12 meses antes | E7: ✓ | F7: =IF(E7="✓","✅ Completado","⏳ Pendiente")
A8: 3 | B8: Contratar wedding planner | C8: Novios | D8: 11 meses antes | E8: ✓ | F8: =IF(E8="✓","✅ Completado","⏳ Pendiente")
A9: 4 | B9: Establecer lista preliminar de invitados | C9: Familia | D9: 10 meses antes | E9: ✓ | F9: =IF(E9="✓","✅ Completado","⏳ Pendiente")
A10: 5 | B10: Elegir fecha y hora del evento | C10: Novios | D10: 11 meses antes | E10: ✓ | F10: =IF(E10="✓","✅ Completado","⏳ Pendiente")
A11: 6 | B11: Definir tema y paleta de colores | C11: Novios + Decorador | D11: 10 meses antes | E11: ✓ | F11: =IF(E11="✓","✅ Completado","⏳ Pendiente")
A12: 7 | B12: Contratar fotógrafo y videógrafo | C12: Planner | D12: 9 meses antes | F12: =IF(E12="✓","✅ Completado","⏳ Pendiente")
A13: 8 | B13: Elegir y reservar banquete/catering | C13: Planner | D13: 9 meses antes | F13: =IF(E13="✓","✅ Completado","⏳ Pendiente")
A14: 9 | B14: Seleccionar tipo de entretenimiento | C14: Novios + Planner | D14: 8 meses antes | F14: =IF(E14="✓","✅ Completado","⏳ Pendiente")
A15: 10 | B15: Abrir registro de mesa de regalos | C15: Novios | D15: 8 meses antes | F15: =IF(E15="✓","✅ Completado","⏳ Pendiente")
A16: 📅 FASE 2: 6-3 MESES ANTES DEL EVENTO
A17: 11 | B17: Elegir vestido de novia/quinceañera | C17: Novia | D17: 6 meses antes | F17: =IF(E17="✓","✅ Completado","⏳ Pendiente")
A18: 12 | B18: Contratar DJ o música en vivo | C18: Planner | D18: 6 meses antes | F18: =IF(E18="✓","✅ Completado","⏳ Pendiente")
A19: 13 | B19: Definir menú del banquete | C19: Pareja + Catering | D19: 5 meses antes | F19: =IF(E19="✓","✅ Completado","⏳ Pendiente")
A20: 14 | B20: Contratar decorador y diseño floral | C20: Planner | D20: 5 meses antes | F20: =IF(E20="✓","✅ Completado","⏳ Pendiente")
A21: 15 | B21: Diseñar e imprimir invitaciones | C21: Planner + Diseñador | D21: 5 meses antes | F21: =IF(E21="✓","✅ Completado","⏳ Pendiente")
A22: 16 | B22: Contratar coreógrafo | C22: Novios | D22: 5 meses antes | F22: =IF(E22="✓","✅ Completado","⏳ Pendiente")
A23: 17 | B23: Reservar hotel para invitados foráneos | C23: Planner | D23: 4 meses antes | F23: =IF(E23="✓","✅ Completado","⏳ Pendiente")
A24: 18 | B24: Contratar maquillista y estilista | C24: Novia | D24: 4 meses antes | F24: =IF(E24="✓","✅ Completado","⏳ Pendiente")
A25: 19 | B25: Enviar invitaciones | C25: Planner | D25: 3 meses antes | F25: =IF(E25="✓","✅ Completado","⏳ Pendiente")
A26: 20 | B26: Contratar transporte para invitados | C26: Planner | D26: 3 meses antes | F26: =IF(E26="✓","✅ Completado","⏳ Pendiente")
A27: 21 | B27: Contratar mariachi o entretenimiento extra | C27: Planner | D27: 3 meses antes | F27: =IF(E27="✓","✅ Completado","⏳ Pendiente")
A28: 22 | B28: Definir diseño de pastel | C28: Novios + Pastelero | D28: 3 meses antes | F28: =IF(E28="✓","✅ Completado","⏳ Pendiente")
A29: 📅 FASE 3: 3-1 MES ANTES DEL EVENTO
A30: 23 | B30: Confirmar todos los proveedores | C30: Planner | D30: 2 meses antes | F30: =IF(E30="✓","✅ Completado","⏳ Pendiente")
A31: 24 | B31: Iniciar clases de baile / ensayos | C31: Novios + Coreógrafo | D31: 2 meses antes | F31: =IF(E31="✓","✅ Completado","⏳ Pendiente")
A32: 25 | B32: Realizar prueba de maquillaje | C32: Novia + Maquillista | D32: 2 meses antes | F32: =IF(E32="✓","✅ Completado","⏳ Pendiente")
A33: 26 | B33: Seguimiento de confirmaciones de invitados | C33: Planner | D33: 6 semanas antes | F33: =IF(E33="✓","✅ Completado","⏳ Pendiente")
A34: 27 | B34: Diseñar seating plan (mesas) | C34: Planner | D34: 1.5 meses antes | F34: =IF(E34="✓","✅ Completado","⏳ Pendiente")
A35: 28 | B35: Coordinar música de ceremonia y recepción | C35: DJ + Planner | D35: 1 mes antes | F35: =IF(E35="✓","✅ Completado","⏳ Pendiente")
A36: 29 | B36: Entregar seating plan final | C36: Planner | D36: 3 semanas antes | F36: =IF(E36="✓","✅ Completado","⏳ Pendiente")
A37: 30 | B37: Confirmar menú definitivo con catering | C37: Planner + Catering | D37: 3 semanas antes | F37: =IF(E37="✓","✅ Completado","⏳ Pendiente")
A38: 31 | B38: Entregar timing del evento a proveedores | C38: Planner | D38: 2 semanas antes | F38: =IF(E38="✓","✅ Completado","⏳ Pendiente")
A39: 32 | B39: Preparar pagos finales | C39: Familia/Novios | D39: 2 semanas antes | F39: =IF(E39="✓","✅ Completado","⏳ Pendiente")
A40: 📅 FASE 4: SEMANA DEL EVENTO
A41: 33 | B41: Confirmar llegada y horarios de proveedores | C41: Planner | D41: 5 días antes | F41: =IF(E41="✓","✅ Completado","⏳ Pendiente")
A42: 34 | B42: Prueba de menú final con catering | C42: Planner + Catering | D42: 5 días antes | F42: =IF(E42="✓","✅ Completado","⏳ Pendiente")
A43: 35 | B43: Preparar kit de emergencia del evento | C43: Planner | D43: 4 días antes | F43: =IF(E43="✓","✅ Completado","⏳ Pendiente")
A44: 36 | B44: Ensayo general de coreografía | C44: Coreógrafo + Novios | D44: 4 días antes | F44: =IF(E44="✓","✅ Completado","⏳ Pendiente")
A45: 37 | B45: Realizar pagos pendientes | C45: Familia/Novios | D45: 3 días antes | F45: =IF(E45="✓","✅ Completado","⏳ Pendiente")
A46: 38 | B46: Confirmar montaje y decoración | C46: Planner + Decorador | D46: 2 días antes | F46: =IF(E46="✓","✅ Completado","⏳ Pendiente")
A47: 39 | B47: Ensayo de ceremonia (si aplica) | C47: Planner + Novios | D47: 2 días antes | F47: =IF(E47="✓","✅ Completado","⏳ Pendiente")
A48: 40 | B48: Supervisar montaje completo | C48: Planner | D48: 1 día antes | F48: =IF(E48="✓","✅ Completado","⏳ Pendiente")
A49: 41 | B49: Confirmar logística de transporte | C49: Planner | D49: 1 día antes | F49: =IF(E49="✓","✅ Completado","⏳ Pendiente")
A50: 42 | B50: Revisar lista final de verificación | C50: Planner | D50: Día del evento | F50: =IF(E50="✓","✅ Completado","⏳ Pendiente")
A51: 43 | B51: Coordinar llegada y bienvenida | C51: Planner + Hostess | D51: Día del evento | F51: =IF(E51="✓","✅ Completado","⏳ Pendiente")
A52: 44 | B52: Supervisión total del evento | C52: Planner + Coordinador | D52: Día del evento | F52: =IF(E52="✓","✅ Completado","⏳ Pendiente")

Sheet 🎨 Diseño
A1: 🎨 DISEÑO & CONCEPTO DEL EVENTO
A2: Define la identidad visual y estética de tu evento
A3: 🎭 TIPO DE EVENTO | F3: 🏛️ MONTAJE & EXPERIENCIA
A4: Tipo de evento | B4: Boda | F4: Tipo de montaje | G4: Banquete con mesas redondas
A5: Estilo principal | B5: Elegante / Romántico | F5: Capacidad por mesa | G5: 10 personas
A6: Paleta de colores | B6: Dorado, Blanco y Verde Salvia | F6: Número de mesas | G6: 15
A7: Número de invitados | B7: 150 | F7: Tipo de sillas | G7: Tiffany en blanco
A8: Presupuesto aprox. | B8: $180,000 MXN | F8: Estilo de mantelería | G8: Lino blanco con caminos dorados
A9: Locación | B9: Hacienda | F9: Iluminación | G9: Cálida + acentos dorados
A10: Temporada | B10: Otoño | F10: Tipo de pista | G10: Pista de madera 6x6m
A11: Hora del día | B11: Tarde-Noche | F11: Escenario / Tarima | G11: Tarima 4x3m para entretenimiento
F12: Área lounge | G12: Sí — zona de descanso VIP
A13: 🎨 PALETA DE COLORES | F13: Área kids | G13: No aplica
A14: Color | B14: Nombre | C14: HEX | D14: Uso en el evento
A15: ████ | B15: Dorado Principal | C15: #C9A84C | D15: Lazos, centros de mesa, detalles
A16: ████ | B16: Blanco Marfil | C16: #FAF7F2 | D16: Mantelería, vestido, altar
A17: ████ | B17: Verde Salvia | C17: #7A9E7E | D17: Flores, hojas decorativas
A18: ████ | B18: Negro Carbón | C18: #1A1A1A | D18: Tipografía, marcos, detalles
A19: ████ | B19: Champagne | C19: #F5E6C0 | D19: Ribbon, fondos, iluminación
A21: 🔗 REFERENCIAS & INSPIRACIÓN
A22: Tipo | B22: Link / Usuario | C22: Notas
A23: Tablero Pinterest | B23: https://pinterest.com/mi-evento | C23: Link al tablero de inspiración
A24: Instagram referencia | B24: @primaveraeventsgroup | C24: Cuenta de referencia visual
A25: Locación referencia | B25: https://primaveraeventsgroup.com | C25: Sitio web del salón
A26: Proveedor flores | B26: https://www.instagram.com/floralstudio | C26: Florería de referencia
A27: Fotógrafo | B27: https://www.luismendozaphoto.com | C27: Portfolio fotógrafo

Sheet 💡 Cotizador
A1: 💡 COTIZADOR AUTOMÁTICO
A2: Resumen de servicios seleccionados — genera tu cotización profesional
A3: ⚡ Este cotizador toma automáticamente los servicios marcados como "✓" en el Catálogo
A4: Categoría | B4: Servicio | C4: Costo Estimado | D4: IVA (16%) | E4: Total c/IVA | F4: Notas
A5: Los servicios seleccionados en el Catálogo aparecerán aquí. Usa la hoja 📦 Catálogo y marca ✓ en columna G.
A7: RESUMEN FINANCIERO
A8: Total servicios seleccionados | C8: ='📦 Catálogo'!E117
A9: IVA (16%) | C9: =C8*0.16
A10: TOTAL CON IVA | C10: =C8+C9
A11: Presupuesto disponible | C11: ='📊 Dashboard'!B10
A12: Diferencia (Disponible - Total) | C12: =C11-C10
A14: 📞 ¿Listo para hacer realidad tu evento? Contáctanos: 📱 WhatsApp: +52 777-123-4567 | 🌐 primaveraeventsgroup.com | 📧 hola@primaveraeventsgroup.com
